scrounter/__init__.py
scrounter/__main__.py
scrounter/src/__init__.py
scrounter/src/reader.py
scrounter/src/writer.py
scrounter-1.0.9.dist-info/METADATA
scrounter-1.0.9.dist-info/WHEEL
scrounter-1.0.9.dist-info/entry_points.txt
scrounter-1.0.9.dist-info/top_level.txt
scrounter-1.0.9.dist-info/RECORD
